adaptive_formula/__init__.py
adaptive_formula/api.py
adaptive_formula/core.cp38-win_amd64.pyd
adaptive_formula/core.cpp
adaptive_formula/core.pyx
adaptive_formula/core_py.py
adaptive_formula/models.py
adaptive_formula-0.4.5.dist-info/LICENSE.txt
adaptive_formula-0.4.5.dist-info/METADATA
adaptive_formula-0.4.5.dist-info/WHEEL
adaptive_formula-0.4.5.dist-info/top_level.txt
adaptive_formula-0.4.5.dist-info/RECORD
