Metadata-Version: 2.1
Name: adaptive-formula
Version: 0.4.5
Summary: Cognitive Programming SDK - Eliminate conditionals with adaptive formulas
Home-page: https://github.com/jaimeajl/adaptive-formula
Author: Jaime Alexander Jimenez Lozano
Author-email: jaimeajl@hotmail.com
License: UNKNOWN
Platform: UNKNOWN
Classifier: Development Status :: 4 - Beta
Classifier: Intended Audience :: Developers
Classifier: License :: Other/Proprietary License
Classifier: Programming Language :: Python :: 3
Classifier: Programming Language :: Python :: 3.7
Classifier: Programming Language :: Python :: 3.8
Classifier: Programming Language :: Python :: 3.9
Classifier: Programming Language :: Python :: 3.10
Classifier: Programming Language :: Python :: 3.11
Classifier: Programming Language :: Python :: 3.12
Classifier: Topic :: Software Development :: Libraries :: Python Modules
Requires-Python: >=3.7
Requires-Dist: requests>=2.25.0
Provides-Extra: full
Requires-Dist: cython>=0.29.0; extra == "full"
Requires-Dist: numpy>=1.19.0; extra == "full"
Requires-Dist: pandas>=1.0.0; extra == "full"
Provides-Extra: optimized
Requires-Dist: cython>=0.29.0; extra == "optimized"
Requires-Dist: numpy>=1.19.0; extra == "optimized"
Provides-Extra: pandas
Requires-Dist: pandas>=1.0.0; extra == "pandas"
